agl_frame2vid/__init__.py
agl_frame2vid/frame2vid.py
agl_frame2vid-0.1.2.dist-info/LICENSE
agl_frame2vid-0.1.2.dist-info/METADATA
agl_frame2vid-0.1.2.dist-info/WHEEL
agl_frame2vid-0.1.2.dist-info/RECORD
