Metadata-Version: 2.1
Name: agl-frame2vid
Version: 0.1.2
Summary: Frame Extraction
License: MIT
Author: Thomas J. Lux
Requires-Python: >3.11,<3.13
Classifier: License :: OSI Approved :: MIT License
Classifier: Programming Language :: Python :: 3
Requires-Dist: numpy (>=1.26.1,<2.0.0)
Requires-Dist: opencv-python (>=4.8.1.78,<5.0.0.0)
Requires-Dist: python-ffmpeg (>=2.0.4,<3.0.0)
